{
  "tiles" : [ {
    "scaleFactors" : [ 32, 16, 8, 4, 2, 1 ],
    "width" : 1024,
    "height" : 1024
  } ],
  "protocol" : "http://iiif.io/api/image",
  "sizes" : [ {
    "width" : 170,
    "height" : 330
  }, {
    "width" : 340,
    "height" : 659
  }, {
    "width" : 680,
    "height" : 1317
  }, {
    "width" : 1359,
    "height" : 2634
  }, {
    "width" : 2717,
    "height" : 5268
  }, {
    "width" : 5434,
    "height" : 10536
  } ],
  "profile" : "http://iiif.io/api/image/2/level0.json",
  "width" : 5434,
  "@id" : "https://sammeltassen.nl/iiif-images/stadsarchief-rotterdam/NL-RtSA_4201_I-118-1/info.json",
  "@context" : "http://iiif.io/api/image/2/context.json",
  "height" : 10536
}